DESCRIPTION.rst
MANIFEST.in
README.rst
setup.cfg
setup.py
bottle_logging/__init__.py
bottle_logging.egg-info/PKG-INFO
bottle_logging.egg-info/SOURCES.txt
bottle_logging.egg-info/dependency_links.txt
bottle_logging.egg-info/requires.txt
bottle_logging.egg-info/top_level.txt